yason/__init__.py
yason/cli.py
yason/yason.py
yason-0.1.4.dist-info/AUTHORS.rst
yason-0.1.4.dist-info/LICENSE
yason-0.1.4.dist-info/METADATA
yason-0.1.4.dist-info/WHEEL
yason-0.1.4.dist-info/entry_points.txt
yason-0.1.4.dist-info/top_level.txt
yason-0.1.4.dist-info/RECORD
