Metadata-Version: 2.1
Name: yason
Version: 0.1.4
Summary: CLI to schedule Jupyter Notebook execution with Papermill and Argo
Home-page: https://github.com/ktaletsk/yason
Author: Konstantin Taletskiy
Author-email: konstantin@taletskiy.com
License: MIT license
Keywords: yason
Platform: UNKNOWN
Classifier: Development Status :: 4 - Beta
Classifier: Intended Audience :: Developers
Classifier: License :: OSI Approved :: MIT License
Classifier: Natural Language :: English
Classifier: Programming Language :: Python :: 3.6
Requires-Dist: Click (>=6.0)
Requires-Dist: boto3 (>=1.9.0)
Requires-Dist: pandas (>=0.20.0)
Requires-Dist: kubernetes (>=9.0.0)
